build/lib/docs/source/conf.py
build/lib/proteinnetpy/__init__.py
build/lib/proteinnetpy/data.py
build/lib/proteinnetpy/maths.py
build/lib/proteinnetpy/mutation.py
build/lib/proteinnetpy/parser.py
build/lib/proteinnetpy/record.py
build/lib/proteinnetpy/tfdataset.py
build/lib/proteinnetpy/scripts/__init__.py
build/lib/proteinnetpy/scripts/add_angles.py
build/lib/proteinnetpy/scripts/filter_proteinnet.py
build/lib/proteinnetpy/scripts/to_fasta.py
docs/source/conf.py
proteinnetpy/__init__.py
proteinnetpy/data.py
proteinnetpy/maths.py
proteinnetpy/mutation.py
proteinnetpy/parser.py
proteinnetpy/record.py
proteinnetpy/tfdataset.py
proteinnetpy/scripts/__init__.py
proteinnetpy/scripts/add_angles.py
proteinnetpy/scripts/filter_proteinnet.py
proteinnetpy/scripts/to_fasta.py
proteinnetpy-1.0.1.dist-info/LICENSE
proteinnetpy-1.0.1.dist-info/METADATA
proteinnetpy-1.0.1.dist-info/WHEEL
proteinnetpy-1.0.1.dist-info/entry_points.txt
proteinnetpy-1.0.1.dist-info/top_level.txt
proteinnetpy-1.0.1.dist-info/zip-safe
proteinnetpy-1.0.1.dist-info/RECORD
