Metadata-Version: 2.1
Name: proteinnetpy
Version: 1.0.1
Summary: Read, process and write ProteinNet data
Author-email: Alistair Dunham <ad44@sanger.ac.uk>
Maintainer-email: Alistair Dunham <ad44@sanger.ac.uk>
License: Copyright 2020 EMBL - European Bioinformatics Institute
Project-URL: Repository, https://github.com/allydunham/proteinnetpy
Project-URL: Documentation, https://proteinnetpy.readthedocs.io/en/latest/
Project-URL: Publication, https://doi.org/10.1186/s13059-023-02948-3
Keywords: protein,bioinformatics,proteinnet,machine learning
Requires-Python: >=3
License-File: LICENSE
Requires-Dist: numpy
Requires-Dist: biopython
Provides-Extra: datasets
Requires-Dist: tensorflow (<3,>=2) ; (sys_platform != "darwin" or platform_machine != "arm64") and extra == 'datasets'
Requires-Dist: tensorflow-macos (<3,>=2) ; (sys_platform == "darwin" and platform_machine == "arm64") and extra == 'datasets'
